e3enrich/E3dict.csv
e3enrich/__init__.py
e3enrich/e3enrich.py
e3enrich/unigenedict.csv
e3enrich-1.0.0.dist-info/LICENSE
e3enrich-1.0.0.dist-info/METADATA
e3enrich-1.0.0.dist-info/WHEEL
e3enrich-1.0.0.dist-info/top_level.txt
e3enrich-1.0.0.dist-info/RECORD
